Workbook

Sheet Inputs
A1: Parámetro | B1: Valor | C1: Unidad | D1: Descripción
A2: Costo LLDPE por kg | B2: 25 | C2: currency/kg | D2: Costo de resina LLDPE por kilogramo
A3: Costo LDPE por kg | B3: 24 | C3: currency/kg | D3: Costo de resina LDPE por kilogramo
A4: Costo HDPE por kg | B4: 22 | C4: currency/kg | D4: Costo de resina HDPE por kilogramo
A5: Costo aditivo UV por kg | B5: 80 | C5: currency/kg | D5: Costo de aditivo UV por kilogramo
A6: Costo de energía por kWh | B6: 1.5 | C6: currency/kWh | D6: Costo de electricidad por kilowatt-hora
A7: Consumo de energía por kg | B7: 0.5 | C7: kWh/kg | D7: Energía utilizada por kg de película producida
A8: Costo de mano de obra por hora | B8: 50 | C8: currency/hour | D8: Costo de mano de obra por hora
A9: Horas de mano de obra por kg | B9: 0.05 | C9: hours/kg | D9: Horas de trabajo necesarias por kg de película
A10: Costo de gastos generales por kg | B10: 5 | C10: currency/kg | D10: Gastos generales asignados por kg
A11: Costo de empaque por kg | B11: 2 | C11: currency/kg | D11: Costo de empaque por kg de película
A12: Porcentaje de margen | B12: 0.2 | C12: % | D12: Margen de ganancia deseado como porcentaje (ej., 20 para 20%)

Sheet Formulations
A1: Tipo de producto | B1: % LLDPE | C1: % LDPE | D1: % HDPE | E1: % aditivo UV | F1: Otros ingredientes
A2: Película natural sin aditivos | B2: 1 | C2: 0 | D2: 0 | E2: 0
A3: Película termoencogible | B3: 0.2 | C3: 0.8 | D3: 0 | E3: 0
A4: Película natural termoencogible con UV 18 meses | B4: 0.2 | C4: 0.78 | D4: 0 | E4: 0.02
A5: Película coex | B5: 0.4 | C5: 0.3 | D5: 0.3 | E5: 0

Sheet Costs
A1: Tipo de producto | B1: Costo de materiales por kg | C1: Costo de energía por kg | D1: Costo de mano de obra por kg | E1: Gastos generales por kg | F1: Costo de empaque por kg | G1: Costo total por kg | H1: Margen (%) | I1: Precio de venta por kg | J1: Utilidad por kg
A2: Película natural sin aditivos | B2: =Formulations!B2*Inputs!B2 + Formulations!C2*Inputs!B3 + Formulations!D2*Inputs!B4 + Formulations!E2*Inputs!B5 -> 25 | C2: =Inputs!B6*Inputs!B7 -> 0.75 | D2: =Inputs!B8*Inputs!B9 -> 2.5 | E2: =Inputs!B10 -> 5 | F2: =Inputs!B11 -> 2 | G2: =SUM(B2:F2) -> 35.25 | H2: =Inputs!B12 -> 0.2 | I2: =G2/(1 - H2) -> 44.0625 | J2: =I2-G2 -> 8.8125
A3: Película termoencogible | B3: =Formulations!B3*Inputs!B2 + Formulations!C3*Inputs!B3 + Formulations!D3*Inputs!B4 + Formulations!E3*Inputs!B5 -> 24.2 | C3: =Inputs!B6*Inputs!B7 -> 0.75 | D3: =Inputs!B8*Inputs!B9 -> 2.5 | E3: =Inputs!B10 -> 5 | F3: =Inputs!B11 -> 2 | G3: =SUM(B3:F3) -> 34.45 | H3: =Inputs!B12 -> 0.2 | I3: =G3/(1 - H3) -> 43.0625 | J3: =I3-G3 -> 8.6125
A4: Película natural termoencogible con UV 18 meses | B4: =Formulations!B4*Inputs!B2 + Formulations!C4*Inputs!B3 + Formulations!D4*Inputs!B4 + Formulations!E4*Inputs!B5 -> 25.32 | C4: =Inputs!B6*Inputs!B7 -> 0.75 | D4: =Inputs!B8*Inputs!B9 -> 2.5 | E4: =Inputs!B10 -> 5 | F4: =Inputs!B11 -> 2 | G4: =SUM(B4:F4) -> 35.57 | H4: =Inputs!B12 -> 0.2 | I4: =G4/(1 - H4) -> 44.4625 | J4: =I4-G4 -> 8.8925
A5: Película coex | B5: =Formulations!B5*Inputs!B2 + Formulations!C5*Inputs!B3 + Formulations!D5*Inputs!B4 + Formulations!E5*Inputs!B5 -> 23.8 | C5: =Inputs!B6*Inputs!B7 -> 0.75 | D5: =Inputs!B8*Inputs!B9 -> 2.5 | E5: =Inputs!B10 -> 5 | F5: =Inputs!B11 -> 2 | G5: =SUM(B5:F5) -> 34.05 | H5: =Inputs!B12 -> 0.2 | I5: =G5/(1 - H5) -> 42.5625 | J5: =I5-G5 -> 8.5125

Sheet Dashboard
A1: Tipo de producto | B1: Costo total por kg | C1: Precio de venta por kg | D1: Utilidad por kg | E1: Margen de utilidad
A2: =Costs!A2 -> Película natural sin aditivos | B2: =Costs!G2 -> 35.25 | C2: =Costs!I2 -> 44.0625 | D2: =Costs!J2 -> 8.8125 | E2: =D2/C2 -> 0.2
A3: =Costs!A3 -> Película termoencogible | B3: =Costs!G3 -> 34.45 | C3: =Costs!I3 -> 43.0625 | D3: =Costs!J3 -> 8.6125 | E3: =D3/C3 -> 0.2
A4: =Costs!A4 -> Película natural termoencogible con UV 18 meses | B4: =Costs!G4 -> 35.57 | C4: =Costs!I4 -> 44.4625 | D4: =Costs!J4 -> 8.8925 | E4: =D4/C4 -> 0.2
A5: =Costs!A5 -> Película coex | B5: =Costs!G5 -> 34.05 | C5: =Costs!I5 -> 42.5625 | D5: =Costs!J5 -> 8.5125 | E5: =D5/C5 -> 0.2

Sheet RunSizes
A1: Tamaño de corrida (kg) | B1: Tipo de producto | C1: Costo total | D1: Precio total de venta | E1: Utilidad total
A2: 200 | B2: =Costs!A2 -> Película natural sin aditivos | C2: =200*Costs!G2 -> 7050 | D2: =200*Costs!I2 -> 8812.5 | E2: =200*Costs!J2 -> 1762.5
A3: 200 | B3: =Costs!A3 -> Película termoencogible | C3: =200*Costs!G3 -> 6890 | D3: =200*Costs!I3 -> 8612.5 | E3: =200*Costs!J3 -> 1722.5
A4: 200 | B4: =Costs!A4 -> Película natural termoencogible con UV 18 meses | C4: =200*Costs!G4 -> 7114 | D4: =200*Costs!I4 -> 8892.5 | E4: =200*Costs!J4 -> 1778.5
A5: 200 | B5: =Costs!A5 -> Película coex | C5: =200*Costs!G5 -> 6810 | D5: =200*Costs!I5 -> 8512.5 | E5: =200*Costs!J5 -> 1702.5
A6: 500 | B6: =Costs!A2 -> Película natural sin aditivos | C6: =500*Costs!G2 -> 17625 | D6: =500*Costs!I2 -> 22031.25 | E6: =500*Costs!J2 -> 4406.25
A7: 500 | B7: =Costs!A3 -> Película termoencogible | C7: =500*Costs!G3 -> 17225 | D7: =500*Costs!I3 -> 21531.25 | E7: =500*Costs!J3 -> 4306.25
A8: 500 | B8: =Costs!A4 -> Película natural termoencogible con UV 18 meses | C8: =500*Costs!G4 -> 17785 | D8: =500*Costs!I4 -> 22231.25 | E8: =500*Costs!J4 -> 4446.25
A9: 500 | B9: =Costs!A5 -> Película coex | C9: =500*Costs!G5 -> 17025 | D9: =500*Costs!I5 -> 21281.25 | E9: =500*Costs!J5 -> 4256.25
A10: 1000 | B10: =Costs!A2 -> Película natural sin aditivos | C10: =1000*Costs!G2 -> 35250 | D10: =1000*Costs!I2 -> 44062.5 | E10: =1000*Costs!J2 -> 8812.5
A11: 1000 | B11: =Costs!A3 -> Película termoencogible | C11: =1000*Costs!G3 -> 34450 | D11: =1000*Costs!I3 -> 43062.5 | E11: =1000*Costs!J3 -> 8612.5
A12: 1000 | B12: =Costs!A4 -> Película natural termoencogible con UV 18 meses | C12: =1000*Costs!G4 -> 35570 | D12: =1000*Costs!I4 -> 44462.5 | E12: =1000*Costs!J4 -> 8892.5
A13: 1000 | B13: =Costs!A5 -> Película coex | C13: =1000*Costs!G5 -> 34050 | D13: =1000*Costs!I5 -> 42562.5 | E13: =1000*Costs!J5 -> 8512.5
A14: 2000 | B14: =Costs!A2 -> Película natural sin aditivos | C14: =2000*Costs!G2 -> 70500 | D14: =2000*Costs!I2 -> 88125 | E14: =2000*Costs!J2 -> 17625
A15: 2000 | B15: =Costs!A3 -> Película termoencogible | C15: =2000*Costs!G3 -> 68900 | D15: =2000*Costs!I3 -> 86125 | E15: =2000*Costs!J3 -> 17225
A16: 2000 | B16: =Costs!A4 -> Película natural termoencogible con UV 18 meses | C16: =2000*Costs!G4 -> 71140 | D16: =2000*Costs!I4 -> 88925 | E16: =2000*Costs!J4 -> 17785
A17: 2000 | B17: =Costs!A5 -> Película coex | C17: =2000*Costs!G5 -> 68100 | D17: =2000*Costs!I5 -> 85125 | E17: =2000*Costs!J5 -> 17025
A18: 5000 | B18: =Costs!A2 -> Película natural sin aditivos | C18: =5000*Costs!G2 -> 176250 | D18: =5000*Costs!I2 -> 220312.5 | E18: =5000*Costs!J2 -> 44062.5
A19: 5000 | B19: =Costs!A3 -> Película termoencogible | C19: =5000*Costs!G3 -> 172250 | D19: =5000*Costs!I3 -> 215312.5 | E19: =5000*Costs!J3 -> 43062.5
A20: 5000 | B20: =Costs!A4 -> Película natural termoencogible con UV 18 meses | C20: =5000*Costs!G4 -> 177850 | D20: =5000*Costs!I4 -> 222312.5 | E20: =5000*Costs!J4 -> 44462.5
A21: 5000 | B21: =Costs!A5 -> Película coex | C21: =5000*Costs!G5 -> 170250 | D21: =5000*Costs!I5 -> 212812.5 | E21: =5000*Costs!J5 -> 42562.5
A22: 10000 | B22: =Costs!A2 -> Película natural sin aditivos | C22: =10000*Costs!G2 -> 352500 | D22: =10000*Costs!I2 -> 440625 | E22: =10000*Costs!J2 -> 88125
A23: 10000 | B23: =Costs!A3 -> Película termoencogible | C23: =10000*Costs!G3 -> 344500 | D23: =10000*Costs!I3 -> 430625 | E23: =10000*Costs!J3 -> 86125
A24: 10000 | B24: =Costs!A4 -> Película natural termoencogible con UV 18 meses | C24: =10000*Costs!G4 -> 355700 | D24: =10000*Costs!I4 -> 444625 | E24: =10000*Costs!J4 -> 88925
A25: 10000 | B25: =Costs!A5 -> Película coex | C25: =10000*Costs!G5 -> 340500 | D25: =10000*Costs!I5 -> 425625 | E25: =10000*Costs!J5 -> 85125
A26: 20000 | B26: =Costs!A2 -> Película natural sin aditivos | C26: =20000*Costs!G2 -> 705000 | D26: =20000*Costs!I2 -> 881250 | E26: =20000*Costs!J2 -> 176250
A27: 20000 | B27: =Costs!A3 -> Película termoencogible | C27: =20000*Costs!G3 -> 689000 | D27: =20000*Costs!I3 -> 861250 | E27: =20000*Costs!J3 -> 172250
A28: 20000 | B28: =Costs!A4 -> Película natural termoencogible con UV 18 meses | C28: =20000*Costs!G4 -> 711400 | D28: =20000*Costs!I4 -> 889250 | E28: =20000*Costs!J4 -> 177850
A29: 20000 | B29: =Costs!A5 -> Película coex | C29: =20000*Costs!G5 -> 681000 | D29: =20000*Costs!I5 -> 851250 | E29: =20000*Costs!J5 -> 170250
A30: 50000 | B30: =Costs!A2 -> Película natural sin aditivos | C30: =50000*Costs!G2 -> 1762500 | D30: =50000*Costs!I2 -> 2203125 | E30: =50000*Costs!J2 -> 440625
A31: 50000 | B31: =Costs!A3 -> Película termoencogible | C31: =50000*Costs!G3 -> 1722500 | D31: =50000*Costs!I3 -> 2153125 | E31: =50000*Costs!J3 -> 430625
A32: 50000 | B32: =Costs!A4 -> Película natural termoencogible con UV 18 meses | C32: =50000*Costs!G4 -> 1778500 | D32: =50000*Costs!I4 -> 2223125 | E32: =50000*Costs!J4 -> 444625
A33: 50000 | B33: =Costs!A5 -> Película coex | C33: =50000*Costs!G5 -> 1702500 | D33: =50000*Costs!I5 -> 2128125 | E33: =50000*Costs!J5 -> 425625

Sheet CostosReales
A1: Parámetro | B1: Valor | C1: Unidad | D1: Descripción
A2: Costo LLDPE por kg | C2: currency/kg | D2: Costo real de LLDPE por kg
A3: Costo LDPE por kg | C3: currency/kg | D3: Costo real de LDPE por kg
A4: Costo HDPE por kg | C4: currency/kg | D4: Costo real de HDPE por kg
A5: Costo aditivo UV por kg | C5: currency/kg | D5: Costo real de aditivo UV por kg
A6: Costo de energía por kWh | C6: currency/kWh | D6: Costo real de electricidad
A7: Consumo de energía por kg | C7: kWh/kg | D7: Consumo real de energía por kg
A8: Costo de mano de obra por hora | C8: currency/hour | D8: Costo real de mano de obra por hora
A9: Horas de mano de obra por kg | C9: hours/kg | D9: Horas reales de mano de obra por kg
A10: Costo de gastos generales por kg | C10: currency/kg | D10: Gastos generales reales por kg
A11: Costo de empaque por kg | C11: currency/kg | D11: Costo real de empaque por kg
A12: Porcentaje de margen | C12: % | D12: Porcentaje de margen deseado
A13: Costo Evita por kg | C13: currency/kg | D13: Otro costo (Evita) por kg

Sheet ResultadosCostos
A1: Tipo de producto | B1: Costo de materiales | C1: Costo de energía | D1: Costo de mano de obra | E1: Costo de producción | F1: Costo de fabricación | G1: Precio de venta | H1: Margen | I1: Margen menos Evita | J1: Fórmula mostrada (Fabricación)
A2: =Formulations!A2 -> Película natural sin aditivos | B2: =Formulations!B2*CostosReales!B2 + Formulations!C2*CostosReales!B3 + Formulations!D2*CostosReales!B4 + Formulations!E2*CostosReales!B5 -> 0 | C2: =CostosReales!B6*CostosReales!B7 -> 0 | D2: =CostosReales!B8*CostosReales!B9 -> 0 | E2: =SUM(B2:D2) -> 0 | F2: =E2 + CostosReales!B10 + CostosReales!B11 -> 0 | G2: =F2/(1 - CostosReales!B12) -> 0 | H2: =G2 - F2 -> 0 | I2: =H2 - CostosReales!B13 -> 0 | J2: Production + Overhead + Packaging; =E2+CostosReales!B10+CostosReales!B11
A3: =Formulations!A3 -> Película termoencogible | B3: =Formulations!B3*CostosReales!B2 + Formulations!C3*CostosReales!B3 + Formulations!D3*CostosReales!B4 + Formulations!E3*CostosReales!B5 -> 0 | C3: =CostosReales!B6*CostosReales!B7 -> 0 | D3: =CostosReales!B8*CostosReales!B9 -> 0 | E3: =SUM(B3:D3) -> 0 | F3: =E3 + CostosReales!B10 + CostosReales!B11 -> 0 | G3: =F3/(1 - CostosReales!B12) -> 0 | H3: =G3 - F3 -> 0 | I3: =H3 - CostosReales!B13 -> 0 | J3: Production + Overhead + Packaging; =E3+CostosReales!B10+CostosReales!B11
A4: =Formulations!A4 -> Película natural termoencogible con UV 18 meses | B4: =Formulations!B4*CostosReales!B2 + Formulations!C4*CostosReales!B3 + Formulations!D4*CostosReales!B4 + Formulations!E4*CostosReales!B5 -> 0 | C4: =CostosReales!B6*CostosReales!B7 -> 0 | D4: =CostosReales!B8*CostosReales!B9 -> 0 | E4: =SUM(B4:D4) -> 0 | F4: =E4 + CostosReales!B10 + CostosReales!B11 -> 0 | G4: =F4/(1 - CostosReales!B12) -> 0 | H4: =G4 - F4 -> 0 | I4: =H4 - CostosReales!B13 -> 0 | J4: Production + Overhead + Packaging; =E4+CostosReales!B10+CostosReales!B11
A5: =Formulations!A5 -> Película coex | B5: =Formulations!B5*CostosReales!B2 + Formulations!C5*CostosReales!B3 + Formulations!D5*CostosReales!B4 + Formulations!E5*CostosReales!B5 -> 0 | C5: =CostosReales!B6*CostosReales!B7 -> 0 | D5: =CostosReales!B8*CostosReales!B9 -> 0 | E5: =SUM(B5:D5) -> 0 | F5: =E5 + CostosReales!B10 + CostosReales!B11 -> 0 | G5: =F5/(1 - CostosReales!B12) -> 0 | H5: =G5 - F5 -> 0 | I5: =H5 - CostosReales!B13 -> 0 | J5: Production + Overhead + Packaging; =E5+CostosReales!B10+CostosReales!B11
